fb_data/.DS_Store
fb_data/__init__.py
fb_data/google_analytics.py
fb_data/google_search_console.py
fb_data/snowflake_helper.py
fb_data/utils.py
fb_data-1.0.0.dist-info/LICENSE
fb_data-1.0.0.dist-info/METADATA
fb_data-1.0.0.dist-info/WHEEL
fb_data-1.0.0.dist-info/RECORD
